elasticsearch_basic_http_logger/__init__.py
elasticsearch_basic_http_logger-0.1.1.dist-info/METADATA
elasticsearch_basic_http_logger-0.1.1.dist-info/WHEEL
elasticsearch_basic_http_logger-0.1.1.dist-info/top_level.txt
elasticsearch_basic_http_logger-0.1.1.dist-info/RECORD
